[
  {
    "dir": "largo",
    "entry": 1736.5,
    "stop": 1729.269,
    "target": 1747.3465,
    "status": "cerrada",
    "ts": 1782098100000,
    "estr": "scalp_rev",
    "coin": "ETH",
    "tf": "5m",
    "fecha": "2026-06-22 03:15:00",
    "funding": 1.25e-05,
    "oi": 804048.7988,
    "pos_rango": 0.57,
    "liq_arriba_%": 0.01,
    "liq_abajo_%": 0.03,
    "exit": 1729.269,
    "pnl": -0.004964123236395045,
    "mfe_R": 0.48,
    "mae_R": 1.37,
    "res": "1m",
    "exits": {
      "fixed": -1.192,
      "be05": -1.192,
      "be10": -1.192,
      "t125": -1.192,
      "trail": -0.708
    }
  },
  {
    "dir": "largo",
    "entry": 1729.5,
    "stop": 1724.8734,
    "target": 1736.4399,
    "status": "cerrada",
    "ts": 1782100500000,
    "estr": "scalp_rev",
    "coin": "ETH",
    "tf": "5m",
    "fecha": "2026-06-22 03:55:00",
    "funding": 1.25e-05,
    "oi": 804048.7988,
    "pos_rango": 0.57,
    "liq_arriba_%": 0.01,
    "liq_abajo_%": 0.03,
    "exit": 1736.4399,
    "pnl": 0.0032126626192541656,
    "mfe_R": 1.66,
    "mae_R": 0.63,
    "res": "1m",
    "exits": {
      "fixed": 1.201,
      "be05": 1.201,
      "be10": 1.201,
      "t125": 0.951,
      "trail": 1.201
    }
  },
  {
    "dir": "largo",
    "entry": 1730.7,
    "stop": 1725.4728,
    "target": 1738.5408000000002,
    "status": "cerrada",
    "ts": 1782100800000,
    "estr": "scalp_rev",
    "coin": "ETH",
    "tf": "5m",
    "fecha": "2026-06-22 04:00:00",
    "funding": 1.25e-05,
    "oi": 804048.7988,
    "pos_rango": 0.57,
    "liq_arriba_%": 0.01,
    "liq_abajo_%": 0.03,
    "exit": 1738.5408000000002,
    "pnl": 0.003730421216848773,
    "mfe_R": 1.76,
    "mae_R": 0.67,
    "res": "1m",
    "exits": {
      "fixed": 1.235,
      "be05": -0.265,
      "be10": 1.235,
      "t125": 0.985,
      "trail": 1.235
    }
  },
  {
    "dir": "corto",
    "entry": 1736.3,
    "stop": 1739.1373999999998,
    "target": 1732.0439000000001,
    "status": "cerrada",
    "ts": 1782105000000,
    "estr": "scalp_rev",
    "coin": "ETH",
    "tf": "5m",
    "fecha": "2026-06-22 05:10:00",
    "funding": 1.25e-05,
    "oi": 804048.7988,
    "pos_rango": 0.57,
    "liq_arriba_%": 0.01,
    "liq_abajo_%": 0.03,
    "exit": 1739.1373999999998,
    "pnl": -0.0024341646028911415,
    "mfe_R": 0.35,
    "mae_R": 1.27,
    "res": "1m",
    "exits": {
      "fixed": -1.49,
      "be05": -1.49,
      "be10": -1.49,
      "t125": -1.49,
      "trail": -1.137
    }
  },
  {
    "dir": "corto",
    "entry": 1737.4,
    "stop": 1741.6399,
    "target": 1731.0401500000003,
    "status": "cerrada",
    "ts": 1782105900000,
    "estr": "scalp_rev",
    "coin": "ETH",
    "tf": "5m",
    "fecha": "2026-06-22 05:25:00",
    "funding": 1.25e-05,
    "oi": 804048.7988,
    "pos_rango": 0.57,
    "liq_arriba_%": 0.01,
    "liq_abajo_%": 0.03,
    "exit": 1741.6399,
    "pnl": -0.00324037066881536,
    "mfe_R": 1.11,
    "mae_R": 1.51,
    "res": "1m",
    "exits": {
      "fixed": -1.328,
      "be05": -0.328,
      "be10": -0.328,
      "t125": -1.328,
      "trail": -0.455
    }
  },
  {
    "dir": "largo",
    "entry": 1734.5,
    "stop": 1731.6666,
    "target": 1738.7501,
    "status": "cerrada",
    "ts": 1782109800000,
    "estr": "scalp_rev",
    "coin": "ETH",
    "tf": "5m",
    "fecha": "2026-06-22 06:30:00",
    "funding": 1.25e-05,
    "oi": 804048.7988,
    "pos_rango": 0.57,
    "liq_arriba_%": 0.01,
    "liq_abajo_%": 0.03,
    "exit": 1738.7501,
    "pnl": 0.0016503315076390745,
    "mfe_R": 2.33,
    "mae_R": 0.64,
    "res": "1m",
    "exits": {
      "fixed": 1.01,
      "be05": 1.01,
      "be10": 1.01,
      "t125": 0.76,
      "trail": -1.066
    }
  },
  {
    "dir": "largo",
    "entry": 1735.1,
    "stop": 1731.267,
    "target": 1740.8494999999998,
    "status": "cerrada",
    "ts": 1782110100000,
    "estr": "scalp_rev",
    "coin": "ETH",
    "tf": "5m",
    "fecha": "2026-06-22 06:35:00",
    "funding": 1.25e-05,
    "oi": 804048.7988,
    "pos_rango": 0.57,
    "liq_arriba_%": 0.01,
    "liq_abajo_%": 0.03,
    "exit": 1740.8494999999998,
    "pnl": 0.002513641865022131,
    "mfe_R": 1.57,
    "mae_R": 0.63,
    "res": "1m",
    "exits": {
      "fixed": 1.138,
      "be05": 1.138,
      "be10": 1.138,
      "t125": 0.888,
      "trail": 1.138
    }
  },
  {
    "dir": "largo",
    "entry": 1734.2,
    "stop": 1730.9673,
    "target": 1739.04905,
    "status": "cerrada",
    "ts": 1782111000000,
    "estr": "scalp_rev",
    "coin": "ETH",
    "tf": "5m",
    "fecha": "2026-06-22 06:50:00",
    "funding": 1.25e-05,
    "oi": 804107.0689999999,
    "pos_rango": 0.55,
    "liq_arriba_%": 0.01,
    "liq_abajo_%": 0.02,
    "exit": 1739.04905,
    "pnl": 0.0019961307807634843,
    "mfe_R": 2.13,
    "mae_R": 0.46,
    "res": "1m",
    "exits": {
      "fixed": 1.071,
      "be05": 1.071,
      "be10": 1.071,
      "t125": 0.821,
      "trail": 1.071
    }
  },
  {
    "dir": "corto",
    "entry": 1740.4,
    "stop": 1742.9411999999998,
    "target": 1736.5882000000006,
    "status": "cerrada",
    "ts": 1782111900000,
    "estr": "scalp_rev",
    "coin": "ETH",
    "tf": "5m",
    "fecha": "2026-06-22 07:05:00",
    "funding": 1.25e-05,
    "oi": 803986.5202000006,
    "pos_rango": 0.67,
    "liq_arriba_%": 0.03,
    "liq_abajo_%": 0.02,
    "exit": 1742.9411999999998,
    "pnl": -0.002260124109399944,
    "mfe_R": 0.71,
    "mae_R": 1.34,
    "res": "1m",
    "exits": {
      "fixed": -1.548,
      "be05": -0.548,
      "be10": -1.548,
      "t125": -1.548,
      "trail": -0.84
    }
  },
  {
    "dir": "corto",
    "entry": 1748.0,
    "stop": 1751.8500999999997,
    "target": 1742.2248500000005,
    "status": "cerrada",
    "ts": 1782113400000,
    "estr": "scalp_rev",
    "coin": "ETH",
    "tf": "5m",
    "fecha": "2026-06-22 07:30:00",
    "funding": 1.25e-05,
    "oi": 803989.3208000001,
    "pos_rango": 0.79,
    "liq_arriba_%": 0.09,
    "liq_abajo_%": 0.01,
    "exit": 1751.8500999999997,
    "pnl": -0.0030025743707091856,
    "mfe_R": 1.27,
    "mae_R": 1.38,
    "res": "1m",
    "exits": {
      "fixed": -1.363,
      "be05": -0.363,
      "be10": -0.363,
      "t125": 0.887,
      "trail": -1.103
    }
  },
  {
    "dir": "corto",
    "entry": 1749.2,
    "stop": 1752.7509999999997,
    "target": 1743.8735000000006,
    "status": "cerrada",
    "ts": 1782113700000,
    "estr": "scalp_rev",
    "coin": "ETH",
    "tf": "5m",
    "fecha": "2026-06-22 07:35:00",
    "funding": 1.25e-05,
    "oi": 803989.3208000001,
    "pos_rango": 0.79,
    "liq_arriba_%": 0.09,
    "liq_abajo_%": 0.01,
    "exit": 1743.8735000000006,
    "pnl": 0.0022451063343239433,
    "mfe_R": 1.55,
    "mae_R": 0.51,
    "res": "1m",
    "exits": {
      "fixed": 1.106,
      "be05": 1.106,
      "be10": 1.106,
      "t125": 0.856,
      "trail": 1.106
    }
  },
  {
    "dir": "corto",
    "entry": 1747.2,
    "stop": 1752.5507999999998,
    "target": 1739.1738000000005,
    "status": "cerrada",
    "ts": 1782114000000,
    "estr": "scalp_rev",
    "coin": "ETH",
    "tf": "5m",
    "fecha": "2026-06-22 07:40:00",
    "funding": 1.25e-05,
    "oi": 803989.3208000001,
    "pos_rango": 0.79,
    "liq_arriba_%": 0.09,
    "liq_abajo_%": 0.01,
    "exit": 1752.5507999999998,
    "pnl": -0.0038624999999998326,
    "mfe_R": 0.77,
    "mae_R": 1.14,
    "res": "1m",
    "exits": {
      "fixed": -1.261,
      "be05": -0.261,
      "be10": -1.261,
      "t125": -1.261,
      "trail": -0.495
    }
  },
  {
    "dir": "largo",
    "entry": 1746.5,
    "stop": 1742.0562,
    "target": 1753.1657,
    "status": "cerrada",
    "ts": 1782121200000,
    "estr": "scalp_rev",
    "coin": "ETH",
    "tf": "5m",
    "fecha": "2026-06-22 09:40:00",
    "funding": 1.25e-05,
    "oi": 800400.9544000002,
    "pos_rango": 0.71,
    "liq_arriba_%": 0.01,
    "liq_abajo_%": 0.01,
    "exit": 1753.1657,
    "pnl": 0.003016604637847132,
    "mfe_R": 1.53,
    "mae_R": 0.47,
    "res": "1m",
    "exits": {
      "fixed": 1.186,
      "be05": -0.314,
      "be10": 1.186,
      "t125": 0.936,
      "trail": 1.186
    }
  },
  {
    "dir": "corto",
    "entry": 1749.0,
    "stop": 1752.4506999999999,
    "target": 1743.8239500000002,
    "status": "cerrada",
    "ts": 1782123000000,
    "estr": "scalp_rev",
    "coin": "ETH",
    "tf": "5m",
    "fecha": "2026-06-22 10:10:00",
    "funding": 1.25e-05,
    "oi": 801174.4098,
    "pos_rango": 0.83,
    "liq_arriba_%": 0.01,
    "liq_abajo_%": 0.01,
    "exit": 1752.4506999999999,
    "pnl": -0.002772955974842693,
    "mfe_R": 0.75,
    "mae_R": 1.25,
    "res": "1m",
    "exits": {
      "fixed": -1.405,
      "be05": -0.405,
      "be10": -1.405,
      "t125": -1.405,
      "trail": -0.71
    }
  },
  {
    "dir": "corto",
    "entry": 1747.8,
    "stop": 1752.1504,
    "target": 1741.2743999999998,
    "status": "cerrada",
    "ts": 1782123300000,
    "estr": "scalp_rev",
    "coin": "ETH",
    "tf": "5m",
    "fecha": "2026-06-22 10:15:00",
    "funding": 1.25e-05,
    "oi": 801174.4098,
    "pos_rango": 0.83,
    "liq_arriba_%": 0.01,
    "liq_abajo_%": 0.01,
    "exit": 1752.1504,
    "pnl": -0.0032890719761986703,
    "mfe_R": 0.32,
    "mae_R": 1.26,
    "res": "1m",
    "exits": {
      "fixed": -1.321,
      "be05": -1.321,
      "be10": -1.321,
      "t125": -1.321,
      "trail": -1.0
    }
  },
  {
    "dir": "corto",
    "entry": 1749.1,
    "stop": 1752.3505999999998,
    "target": 1744.2241000000001,
    "status": "cerrada",
    "ts": 1782124200000,
    "estr": "scalp_rev",
    "coin": "ETH",
    "tf": "5m",
    "fecha": "2026-06-22 10:30:00",
    "funding": 1.25e-05,
    "oi": 801652.4673999997,
    "pos_rango": 0.84,
    "liq_arriba_%": 0.01,
    "liq_abajo_%": 0.01,
    "exit": 1752.3505999999998,
    "pnl": -0.002658441484191784,
    "mfe_R": 0.83,
    "mae_R": 1.29,
    "res": "1m",
    "exits": {
      "fixed": -1.43,
      "be05": -0.43,
      "be10": -1.43,
      "t125": -1.43,
      "trail": -0.631
    }
  },
  {
    "dir": "corto",
    "entry": 1751.4,
    "stop": 1755.2534999999998,
    "target": 1745.6197500000005,
    "status": "cerrada",
    "ts": 1782126600000,
    "estr": "scalp_rev",
    "coin": "ETH",
    "tf": "5m",
    "fecha": "2026-06-22 11:10:00",
    "funding": 1.25e-05,
    "oi": 801368.7838000001,
    "pos_rango": 0.8,
    "liq_arriba_%": 0.01,
    "liq_abajo_%": 0.09,
    "exit": 1755.2534999999998,
    "pnl": -0.003000239808153313,
    "mfe_R": 0.8,
    "mae_R": 1.19,
    "res": "1m",
    "exits": {
      "fixed": -1.364,
      "be05": -0.364,
      "be10": -1.364,
      "t125": -1.364,
      "trail": -0.559
    }
  },
  {
    "dir": "corto",
    "entry": 1752.2,
    "stop": 1756.0542999999998,
    "target": 1746.4185500000003,
    "status": "cerrada",
    "ts": 1782127500000,
    "estr": "scalp_rev",
    "coin": "ETH",
    "tf": "5m",
    "fecha": "2026-06-22 11:25:00",
    "funding": 1.25e-05,
    "oi": 807748.4657999995,
    "pos_rango": 0.96,
    "liq_arriba_%": 0.03,
    "liq_abajo_%": 0.12,
    "exit": 1756.0542999999998,
    "pnl": -0.0029996918160025902,
    "mfe_R": 0.44,
    "mae_R": 2.44,
    "res": "1m",
    "exits": {
      "fixed": -1.364,
      "be05": -1.364,
      "be10": -1.364,
      "t125": -1.364,
      "trail": -0.923
    }
  },
  {
    "dir": "corto",
    "entry": 1767.1,
    "stop": 1775.8740999999998,
    "target": 1753.93885,
    "status": "cerrada",
    "ts": 1782129000000,
    "estr": "scalp_rev",
    "coin": "ETH",
    "tf": "5m",
    "fecha": "2026-06-22 11:50:00",
    "funding": 1.25e-05,
    "oi": 809839.2472000001,
    "pos_rango": 0.85,
    "liq_arriba_%": 0.08,
    "liq_abajo_%": 0.01,
    "exit": 1775.8740999999998,
    "pnl": -0.00576525380567023,
    "mfe_R": 0.87,
    "mae_R": 1.3,
    "res": "1m",
    "exits": {
      "fixed": -1.161,
      "be05": -0.161,
      "be10": -1.161,
      "t125": -1.161,
      "trail": -0.295
    }
  },
  {
    "dir": "corto",
    "entry": 1764.6,
    "stop": 1771.9701999999997,
    "target": 1753.5447000000001,
    "status": "cerrada",
    "ts": 1782135000000,
    "estr": "scalp_rev",
    "coin": "ETH",
    "tf": "5m",
    "fecha": "2026-06-22 13:30:00",
    "funding": 1.4711e-06,
    "oi": 822444.1986000001,
    "pos_rango": 0.77,
    "liq_arriba_%": 0.02,
    "liq_abajo_%": 0.03,
    "exit": 1771.9701999999997,
    "pnl": -0.0049766972685026875,
    "mfe_R": 0.43,
    "mae_R": 1.89,
    "res": "1m",
    "exits": {
      "fixed": -1.192,
      "be05": -1.192,
      "be10": -1.192,
      "t125": -1.192,
      "trail": -0.757
    }
  },
  {
    "dir": "corto",
    "entry": 1772.6,
    "stop": 1776.0742999999998,
    "target": 1767.3885500000001,
    "status": "cerrada",
    "ts": 1782135900000,
    "estr": "scalp_rev",
    "coin": "ETH",
    "tf": "5m",
    "fecha": "2026-06-22 13:45:00",
    "funding": 1.0465e-06,
    "oi": 828665.6637999999,
    "pos_rango": 0.87,
    "liq_arriba_%": 0.08,
    "liq_abajo_%": 0.15,
    "exit": 1776.0742999999998,
    "pnl": -0.0027600022565721864,
    "mfe_R": 0.75,
    "mae_R": 1.09,
    "res": "1m",
    "exits": {
      "fixed": -1.408,
      "be05": -0.408,
      "be10": -1.408,
      "t125": -1.408,
      "trail": -0.66
    }
  },
  {
    "dir": "largo",
    "entry": 1754.9,
    "stop": 1752.5457,
    "target": 1758.4314500000005,
    "status": "cerrada",
    "ts": 1782138300000,
    "estr": "scalp_rev",
    "coin": "ETH",
    "tf": "5m",
    "fecha": "2026-06-22 14:25:00",
    "funding": -8.151e-07,
    "oi": 814692.4261999985,
    "pos_rango": 0.49,
    "liq_arriba_%": 0.1,
    "liq_abajo_%": 0.05,
    "exit": 1758.4314500000005,
    "pnl": 0.0012123368852928395,
    "mfe_R": 2.0,
    "mae_R": 0.0,
    "res": "1m",
    "exits": {
      "fixed": 0.904,
      "be05": 0.904,
      "be10": 0.904,
      "t125": 0.654,
      "trail": 0.904
    }
  },
  {
    "dir": "largo",
    "entry": 1755.9,
    "stop": 1748.5497,
    "target": 1766.9254500000002,
    "status": "cerrada",
    "ts": 1782138600000,
    "estr": "scalp_rev",
    "coin": "ETH",
    "tf": "5m",
    "fecha": "2026-06-22 14:30:00",
    "funding": -8.151e-07,
    "oi": 814692.4261999985,
    "pos_rango": 0.49,
    "liq_arriba_%": 0.1,
    "liq_abajo_%": 0.05,
    "exit": 1748.5497,
    "pnl": -0.004986058431573587,
    "mfe_R": 0.34,
    "mae_R": 1.62,
    "res": "1m",
    "exits": {
      "fixed": -1.191,
      "be05": -1.191,
      "be10": -1.191,
      "t125": -1.191,
      "trail": -0.851
    }
  },
  {
    "dir": "largo",
    "entry": 1733.8,
    "stop": 1728.6696000000002,
    "target": 1741.4955999999997,
    "status": "cerrada",
    "ts": 1782149700000,
    "estr": "scalp_rev",
    "coin": "ETH",
    "tf": "5m",
    "fecha": "2026-06-22 17:35:00",
    "funding": 5.5536e-06,
    "oi": 789470.5098000007,
    "pos_rango": 0.13,
    "liq_arriba_%": 0.02,
    "liq_abajo_%": 0.03,
    "exit": 1741.4955999999997,
    "pnl": 0.0036385742300148734,
    "mfe_R": 1.56,
    "mae_R": 0.66,
    "res": "1m",
    "exits": {
      "fixed": 1.23,
      "be05": 1.23,
      "be10": 1.23,
      "t125": 0.98,
      "trail": 1.23
    }
  },
  {
    "dir": "corto",
    "entry": 1745.1,
    "stop": 1747.3455999999996,
    "target": 1741.7316000000003,
    "status": "cerrada",
    "ts": 1782151500000,
    "estr": "scalp_rev",
    "coin": "ETH",
    "tf": "5m",
    "fecha": "2026-06-22 18:05:00",
    "sesion": "ny",
    "funding": 1.25e-05,
    "oi": 788250.7148,
    "d_oi_%": null,
    "fng": 20,
    "pos_rango": 0.29,
    "liq_arriba_%": 0.03,
    "liq_abajo_%": 0.01,
    "atr_%": 0.177,
    "adx": 26.5,
    "regimen": "tendencia",
    "vol_rel": 0.25,
    "exit": 1741.7316000000003,
    "pnl": 0.0011302045728036276,
    "mfe_R": 2.23,
    "mae_R": 0.76,
    "res": "1m",
    "exits": {
      "fixed": 0.878,
      "be05": -0.622,
      "be10": -0.622,
      "t125": 0.628,
      "trail": -0.597
    }
  },
  {
    "dir": "corto",
    "entry": 1744.3,
    "stop": 1748.5467999999998,
    "target": 1737.9298000000001,
    "status": "cerrada",
    "ts": 1782152100000,
    "estr": "scalp_rev",
    "coin": "ETH",
    "tf": "5m",
    "fecha": "2026-06-22 18:15:00",
    "sesion": "ny",
    "funding": 1.25e-05,
    "oi": 788250.7148,
    "d_oi_%": null,
    "fng": 20,
    "pos_rango": 0.29,
    "liq_arriba_%": 0.03,
    "liq_abajo_%": 0.01,
    "atr_%": 0.177,
    "adx": 26.5,
    "regimen": "tendencia",
    "vol_rel": 0.25,
    "exit": 1737.9298000000001,
    "pnl": 0.0028520094020523076,
    "mfe_R": 2.28,
    "mae_R": 0.59,
    "res": "1m",
    "exits": {
      "fixed": 1.171,
      "be05": 1.171,
      "be10": 1.171,
      "t125": 0.921,
      "trail": 1.171
    }
  },
  {
    "dir": "largo",
    "entry": 1732.6,
    "stop": 1727.1711,
    "target": 1740.7433499999997,
    "status": "cerrada",
    "ts": 1782154500000,
    "estr": "scalp_rev",
    "coin": "ETH",
    "tf": "5m",
    "fecha": "2026-06-22 18:55:00",
    "sesion": "ny",
    "funding": 1.25e-05,
    "oi": 825505.9756000001,
    "d_oi_%": 2.46,
    "fng": 20,
    "pos_rango": 0.07,
    "liq_arriba_%": 0.12,
    "liq_abajo_%": 0.01,
    "atr_%": 0.19,
    "adx": 25.8,
    "regimen": "tendencia",
    "vol_rel": 0.43,
    "exit": 1727.1711,
    "pnl": -0.0039333833544960665,
    "mfe_R": 1.25,
    "mae_R": 1.14,
    "res": "1m",
    "exits": {
      "fixed": -1.255,
      "be05": -0.255,
      "be10": -0.255,
      "t125": 0.995,
      "trail": -0.758
    }
  },
  {
    "dir": "largo",
    "entry": 1730.7,
    "stop": 1726.7715,
    "target": 1736.59275,
    "status": "cerrada",
    "ts": 1782155100000,
    "estr": "scalp_rev",
    "coin": "ETH",
    "tf": "5m",
    "fecha": "2026-06-22 19:05:00",
    "sesion": "ny",
    "funding": 1.25e-05,
    "oi": 844880.1912000001,
    "d_oi_%": 7.18,
    "fng": 20,
    "pos_rango": 0.14,
    "liq_arriba_%": 0.08,
    "liq_abajo_%": 0.06,
    "atr_%": 0.198,
    "adx": 28.3,
    "regimen": "tendencia",
    "vol_rel": 0.06,
    "exit": 1736.59275,
    "pnl": 0.002604836193447725,
    "mfe_R": 1.86,
    "mae_R": 0.64,
    "res": "1m",
    "exits": {
      "fixed": 1.148,
      "be05": -0.352,
      "be10": -0.352,
      "t125": 0.898,
      "trail": 0.073
    }
  },
  {
    "dir": "largo",
    "entry": 1731.8,
    "stop": 1727.8704,
    "target": 1737.6943999999999,
    "status": "cerrada",
    "ts": 1782161400000,
    "estr": "scalp_rev",
    "coin": "ETH",
    "tf": "5m",
    "fecha": "2026-06-22 20:50:00",
    "sesion": "ny",
    "funding": 1.25e-05,
    "oi": 805523.3280000001,
    "d_oi_%": -4.38,
    "fng": 20,
    "pos_rango": 0.07,
    "liq_arriba_%": 0.03,
    "liq_abajo_%": 0.03,
    "atr_%": 0.163,
    "adx": 23.2,
    "regimen": "rango",
    "vol_rel": 4.55,
    "exit": 1727.8704,
    "pnl": -0.0030690841898602245,
    "mfe_R": 1.22,
    "mae_R": 1.37,
    "res": "1m",
    "exits": {
      "fixed": -1.353,
      "be05": -0.353,
      "be10": -0.353,
      "t125": -1.353,
      "trail": -0.564
    }
  },
  {
    "dir": "largo",
    "entry": 1731.2,
    "stop": 1728.4698,
    "target": 1735.2953,
    "status": "cerrada",
    "ts": 1782163200000,
    "estr": "scalp_rev",
    "coin": "ETH",
    "tf": "5m",
    "fecha": "2026-06-22 21:20:00",
    "sesion": "cierre",
    "funding": 1.3536e-06,
    "oi": 806130.2671999999,
    "d_oi_%": -2.74,
    "fng": 20,
    "pos_rango": 0.06,
    "liq_arriba_%": 0.07,
    "liq_abajo_%": 0.01,
    "atr_%": 0.136,
    "adx": 23.2,
    "regimen": "rango",
    "vol_rel": 1.41,
    "exit": 1728.4698,
    "pnl": -0.002377056377079464,
    "mfe_R": 0.99,
    "mae_R": 1.76,
    "res": "1m",
    "exits": {
      "fixed": -1.507,
      "be05": -0.507,
      "be10": -1.507,
      "t125": -1.507,
      "trail": -0.518
    }
  },
  {
    "dir": "largo",
    "entry": 1733.1,
    "stop": 1729.0692,
    "target": 1739.1462,
    "status": "cerrada",
    "ts": 1782163500000,
    "estr": "scalp_rev",
    "coin": "ETH",
    "tf": "5m",
    "fecha": "2026-06-22 21:25:00",
    "sesion": "cierre",
    "funding": -3.243e-07,
    "oi": 796352.1122000001,
    "d_oi_%": -5.6,
    "fng": 20,
    "pos_rango": 0.02,
    "liq_arriba_%": 0.28,
    "liq_abajo_%": 0.07,
    "atr_%": 0.145,
    "adx": 26.3,
    "regimen": "tendencia",
    "vol_rel": 0.24,
    "exit": 1729.0692,
    "pnl": -0.0031257746235070103,
    "mfe_R": 0.05,
    "mae_R": 1.66,
    "res": "1m",
    "exits": {
      "fixed": -1.344,
      "be05": -1.344,
      "be10": -1.344,
      "t125": -1.344,
      "trail": -1.294
    }
  },
  {
    "dir": "largo",
    "entry": 1730.8,
    "stop": 1726.272,
    "target": 1737.592,
    "status": "cerrada",
    "ts": 1782164700000,
    "estr": "scalp_rev",
    "coin": "ETH",
    "tf": "5m",
    "fecha": "2026-06-22 21:45:00",
    "sesion": "cierre",
    "funding": 2.7039e-06,
    "oi": 787024.4425999998,
    "d_oi_%": -2.3,
    "fng": 20,
    "pos_rango": 0.07,
    "liq_arriba_%": 0.01,
    "liq_abajo_%": 0.01,
    "atr_%": 0.159,
    "adx": 28.9,
    "regimen": "tendencia",
    "vol_rel": 0.06,
    "exit": 1726.272,
    "pnl": -0.0034161312687774554,
    "mfe_R": 0.93,
    "mae_R": 1.44,
    "res": "1m",
    "exits": {
      "fixed": -1.306,
      "be05": -0.306,
      "be10": -1.306,
      "t125": -1.306,
      "trail": -0.378
    }
  },
  {
    "dir": "largo",
    "entry": 1724.5,
    "stop": 1717.4808,
    "target": 1735.0288,
    "status": "cerrada",
    "ts": 1782167400000,
    "estr": "scalp_rev",
    "coin": "ETH",
    "tf": "5m",
    "fecha": "2026-06-22 22:30:00",
    "sesion": "cierre",
    "funding": 1.18491e-05,
    "oi": 793222.2719999998,
    "d_oi_%": -0.39,
    "fng": 20,
    "pos_rango": 0.03,
    "liq_arriba_%": 0.38,
    "liq_abajo_%": 0.06,
    "atr_%": 0.235,
    "adx": 32.5,
    "regimen": "tendencia",
    "vol_rel": 2.16,
    "exit": 1717.4808,
    "pnl": -0.004870281240939378,
    "mfe_R": 0.01,
    "mae_R": 1.14,
    "res": "1m",
    "exits": {
      "fixed": -1.197,
      "be05": -1.197,
      "be10": -1.197,
      "t125": -1.197,
      "trail": -1.182
    }
  },
  {
    "dir": "largo",
    "entry": 1721.1,
    "stop": 1716.4818,
    "target": 1728.0272999999997,
    "status": "cerrada",
    "ts": 1782168300000,
    "estr": "scalp_rev",
    "coin": "ETH",
    "tf": "5m",
    "fecha": "2026-06-22 22:45:00",
    "sesion": "cierre",
    "funding": 1.25e-05,
    "oi": 794267.5335999997,
    "d_oi_%": 0.92,
    "fng": 20,
    "pos_rango": 0.17,
    "liq_arriba_%": 0.06,
    "liq_abajo_%": 0.15,
    "atr_%": 0.235,
    "adx": 37.3,
    "regimen": "tendencia",
    "vol_rel": 0.41,
    "exit": 1728.0272999999997,
    "pnl": 0.0032249259194700093,
    "mfe_R": 2.1,
    "mae_R": 0.39,
    "res": "1m",
    "exits": {
      "fixed": 1.202,
      "be05": -0.298,
      "be10": 1.202,
      "t125": 0.952,
      "trail": 1.202
    }
  },
  {
    "dir": "largo",
    "entry": 1721.1,
    "stop": 1718.0801999999999,
    "target": 1725.6297,
    "status": "cerrada",
    "ts": 1782174300000,
    "estr": "scalp_rev",
    "coin": "ETH",
    "tf": "5m",
    "fecha": "2026-06-23 00:25:00",
    "sesion": "asia",
    "funding": 1.25e-05,
    "oi": 826797.4434,
    "d_oi_%": -0.22,
    "fng": 23,
    "pos_rango": 0.15,
    "liq_arriba_%": 0.02,
    "liq_abajo_%": 0.01,
    "atr_%": 0.146,
    "adx": 23.4,
    "regimen": "rango",
    "vol_rel": 0.7,
    "exit": 1725.6297,
    "pnl": 0.0018318633432107653,
    "mfe_R": 1.82,
    "mae_R": 0.43,
    "res": "1m",
    "exits": {
      "fixed": 1.044,
      "be05": 1.044,
      "be10": 1.044,
      "t125": 0.794,
      "trail": 1.044
    }
  },
  {
    "dir": "corto",
    "entry": 1732.3,
    "stop": 1734.9332,
    "target": 1728.3501999999999,
    "status": "cerrada",
    "ts": 1782176700000,
    "estr": "scalp_rev",
    "coin": "ETH",
    "tf": "5m",
    "fecha": "2026-06-23 01:05:00",
    "sesion": "asia",
    "funding": 1.25e-05,
    "oi": 835566.9698000001,
    "d_oi_%": -0.02,
    "fng": 23,
    "pos_rango": 0.52,
    "liq_arriba_%": 0.01,
    "liq_abajo_%": 0.01,
    "atr_%": 0.166,
    "adx": 20.7,
    "regimen": "rango",
    "vol_rel": 0.13,
    "exit": 1728.3501999999999,
    "pnl": 0.0014800900536859063,
    "mfe_R": 1.82,
    "mae_R": 0.99,
    "res": "1m",
    "exits": {
      "fixed": 0.974,
      "be05": 0.974,
      "be10": 0.974,
      "t125": 0.724,
      "trail": -1.033
    }
  },
  {
    "dir": "corto",
    "entry": 1732.0,
    "stop": 1736.6348999999998,
    "target": 1725.0476500000004,
    "status": "cerrada",
    "ts": 1782177600000,
    "estr": "scalp_rev",
    "coin": "ETH",
    "tf": "5m",
    "fecha": "2026-06-23 01:20:00",
    "sesion": "asia",
    "funding": 1.25e-05,
    "oi": 836737.2746,
    "d_oi_%": 0.14,
    "fng": 23,
    "pos_rango": 0.51,
    "liq_arriba_%": 0.01,
    "liq_abajo_%": 0.01,
    "atr_%": 0.166,
    "adx": 23.6,
    "regimen": "rango",
    "vol_rel": 0.84,
    "exit": 1725.0476500000004,
    "pnl": 0.0032140588914547174,
    "mfe_R": 1.73,
    "mae_R": 0.63,
    "res": "1m",
    "exits": {
      "fixed": 1.201,
      "be05": 1.201,
      "be10": 1.201,
      "t125": 0.951,
      "trail": 1.201
    }
  },
  {
    "dir": "largo",
    "entry": 1726.8,
    "stop": 1722.276,
    "target": 1733.5859999999998,
    "status": "cerrada",
    "ts": 1782188400000,
    "estr": "scalp_rev",
    "coin": "ETH",
    "tf": "5m",
    "fecha": "2026-06-23 04:20:00",
    "sesion": "asia",
    "funding": 1.25e-05,
    "oi": 818751.0924,
    "d_oi_%": -0.7,
    "fng": 23,
    "pos_rango": 0.46,
    "liq_arriba_%": 0.02,
    "liq_abajo_%": 0.01,
    "atr_%": 0.117,
    "adx": 10.9,
    "regimen": "rango",
    "vol_rel": 7.97,
    "exit": 1722.276,
    "pnl": -0.0034198749131340556,
    "mfe_R": 0.11,
    "mae_R": 1.13,
    "res": "1m",
    "exits": {
      "fixed": -1.305,
      "be05": -1.305,
      "be10": -1.305,
      "t125": -1.305,
      "trail": -1.195
    }
  },
  {
    "dir": "largo",
    "entry": 1722.2,
    "stop": 1719.8783999999998,
    "target": 1725.6824000000004,
    "status": "cerrada",
    "ts": 1782189900000,
    "estr": "scalp_rev",
    "coin": "ETH",
    "tf": "5m",
    "fecha": "2026-06-23 04:45:00",
    "sesion": "asia",
    "funding": 1.10622e-05,
    "oi": 823940.8760000014,
    "d_oi_%": -0.02,
    "fng": 23,
    "pos_rango": 0.28,
    "liq_arriba_%": 0.06,
    "liq_abajo_%": 0.01,
    "atr_%": 0.118,
    "adx": 18.2,
    "regimen": "rango",
    "vol_rel": 0.07,
    "exit": 1719.8783999999998,
    "pnl": -0.0021480432005575524,
    "mfe_R": 0.52,
    "mae_R": 1.38,
    "res": "1m",
    "exits": {
      "fixed": -1.593,
      "be05": -0.593,
      "be10": -1.593,
      "t125": -1.593,
      "trail": -1.077
    }
  },
  {
    "dir": "largo",
    "entry": 1720.5,
    "stop": 1716.3818999999999,
    "target": 1726.6771500000002,
    "status": "cerrada",
    "ts": 1782190800000,
    "estr": "scalp_rev",
    "coin": "ETH",
    "tf": "5m",
    "fecha": "2026-06-23 05:00:00",
    "sesion": "asia",
    "funding": 6.94e-06,
    "oi": 825732.5791999997,
    "d_oi_%": 0.22,
    "fng": 23,
    "pos_rango": 0.2,
    "liq_arriba_%": 0.03,
    "liq_abajo_%": 0.04,
    "atr_%": 0.14,
    "adx": 25.3,
    "regimen": "tendencia",
    "vol_rel": 0.34,
    "exit": 1716.3818999999999,
    "pnl": -0.003193548387096856,
    "mfe_R": 0.0,
    "mae_R": 1.17,
    "res": "1m",
    "exits": {
      "fixed": -1.334,
      "be05": -1.334,
      "be10": -1.334,
      "t125": -1.334,
      "trail": -1.334
    }
  },
  {
    "dir": "largo",
    "entry": 1719.3,
    "stop": 1715.1831000000002,
    "target": 1725.4753499999997,
    "status": "cerrada",
    "ts": 1782191100000,
    "estr": "scalp_rev",
    "coin": "ETH",
    "tf": "5m",
    "fecha": "2026-06-23 05:05:00",
    "sesion": "asia",
    "funding": 7.2144e-06,
    "oi": 826755.8701999999,
    "d_oi_%": 0.31,
    "fng": 23,
    "pos_rango": 0.14,
    "liq_arriba_%": 0.07,
    "liq_abajo_%": 0.01,
    "atr_%": 0.151,
    "adx": 27.7,
    "regimen": "tendencia",
    "vol_rel": 1.42,
    "exit": 1715.1831000000002,
    "pnl": -0.003194521025998813,
    "mfe_R": 0.27,
    "mae_R": 1.26,
    "res": "1m",
    "exits": {
      "fixed": -1.334,
      "be05": -1.334,
      "be10": -1.334,
      "t125": -1.334,
      "trail": -1.067
    }
  },
  {
    "dir": "largo",
    "entry": 1712.6,
    "stop": 1707.5907,
    "target": 1720.11395,
    "status": "cerrada",
    "ts": 1782192300000,
    "estr": "scalp_rev",
    "coin": "ETH",
    "tf": "5m",
    "fecha": "2026-06-23 05:25:00",
    "sesion": "asia",
    "funding": -2.3363e-06,
    "oi": 807581.5216000001,
    "d_oi_%": -1.71,
    "fng": 23,
    "pos_rango": 0.12,
    "liq_arriba_%": 0.04,
    "liq_abajo_%": 0.18,
    "atr_%": 0.185,
    "adx": 38.5,
    "regimen": "tendencia",
    "vol_rel": 0.24,
    "exit": 1707.5907,
    "pnl": -0.003724967885086967,
    "mfe_R": 0.32,
    "mae_R": 2.04,
    "res": "1m",
    "exits": {
      "fixed": -1.274,
      "be05": -1.274,
      "be10": -1.274,
      "t125": -1.274,
      "trail": -0.954
    }
  },
  {
    "dir": "largo",
    "entry": 1705.9,
    "stop": 1700.6976000000002,
    "target": 1713.7035999999998,
    "status": "cerrada",
    "ts": 1782194700000,
    "estr": "scalp_rev",
    "coin": "ETH",
    "tf": "5m",
    "fecha": "2026-06-23 06:05:00",
    "sesion": "asia",
    "funding": 8.1735e-06,
    "oi": 802220.3333999993,
    "d_oi_%": -0.16,
    "fng": 23,
    "pos_rango": 0.1,
    "liq_arriba_%": 0.31,
    "liq_abajo_%": 0.21,
    "atr_%": 0.213,
    "adx": 52.8,
    "regimen": "tendencia",
    "vol_rel": 3.0,
    "exit": 1700.6976000000002,
    "pnl": -0.003849651210504659,
    "mfe_R": 1.02,
    "mae_R": 2.56,
    "res": "1m",
    "exits": {
      "fixed": -1.262,
      "be05": -0.262,
      "be10": -0.262,
      "t125": -1.262,
      "trail": -0.244
    }
  },
  {
    "dir": "largo",
    "entry": 1706.4,
    "stop": 1702.5956999999999,
    "target": 1712.1064500000005,
    "status": "cerrada",
    "ts": 1782195000000,
    "estr": "scalp_rev",
    "coin": "ETH",
    "tf": "5m",
    "fecha": "2026-06-23 06:10:00",
    "sesion": "asia",
    "funding": 8.6527e-06,
    "oi": 802223.6481999999,
    "d_oi_%": -0.16,
    "fng": null,
    "pos_rango": 0.12,
    "liq_arriba_%": 0.1,
    "liq_abajo_%": 0.12,
    "atr_%": 0.219,
    "adx": 54.8,
    "regimen": "tendencia",
    "vol_rel": 0.23,
    "exit": 1702.5956999999999,
    "pnl": -0.0030294303797469757,
    "mfe_R": 0.53,
    "mae_R": 1.5,
    "res": "1m",
    "exits": {
      "fixed": -1.359,
      "be05": -0.359,
      "be10": -1.359,
      "t125": -1.359,
      "trail": -0.833
    }
  },
  {
    "dir": "largo",
    "entry": 1688.5,
    "stop": 1681.2171,
    "target": 1699.4243499999998,
    "status": "cerrada",
    "ts": 1782196200000,
    "estr": "scalp_rev",
    "coin": "ETH",
    "tf": "5m",
    "fecha": "2026-06-23 06:30:00",
    "sesion": "asia",
    "funding": 8.5888e-06,
    "oi": 791098.345,
    "d_oi_%": -0.27,
    "fng": 23,
    "pos_rango": 0.14,
    "liq_arriba_%": 0.06,
    "liq_abajo_%": 0.33,
    "atr_%": 0.328,
    "adx": 63.0,
    "regimen": "tendencia",
    "vol_rel": 0.61,
    "exit": 1681.2171,
    "pnl": -0.005113236600532974,
    "mfe_R": 0.95,
    "mae_R": 1.18,
    "res": "1m",
    "exits": {
      "fixed": -1.185,
      "be05": -0.185,
      "be10": -1.185,
      "t125": -1.185,
      "trail": -0.238
    }
  },
  {
    "dir": "largo",
    "entry": 1680.0,
    "stop": 1676.1222,
    "target": 1685.8166999999999,
    "status": "cerrada",
    "ts": 1782201900000,
    "estr": "scalp_rev",
    "coin": "ETH",
    "tf": "5m",
    "fecha": "2026-06-23 08:05:00",
    "sesion": "londres",
    "funding": -2.7442e-05,
    "oi": 736680.8892000007,
    "d_oi_%": -6.99,
    "fng": 23,
    "pos_rango": 0.04,
    "liq_arriba_%": 0.06,
    "liq_abajo_%": 0.01,
    "atr_%": 0.196,
    "adx": 60.7,
    "regimen": "tendencia",
    "vol_rel": 0.74,
    "exit": 1676.1222,
    "pnl": -0.003108214285714273,
    "mfe_R": 0.46,
    "mae_R": 1.21,
    "res": "1m",
    "exits": {
      "fixed": -1.347,
      "be05": -1.347,
      "be10": -1.347,
      "t125": -1.347,
      "trail": -0.882
    }
  },
  {
    "dir": "largo",
    "entry": 1647.9,
    "stop": 1638.9594,
    "target": 1661.3109000000004,
    "status": "abierta",
    "ts": 1782203400000,
    "estr": "scalp_rev",
    "coin": "ETH",
    "tf": "5m",
    "fecha": "2026-06-23 08:30:00",
    "sesion": "londres",
    "funding": -2.7442e-05,
    "oi": 736680.8892000007,
    "d_oi_%": -6.99,
    "fng": 23,
    "pos_rango": 0.14,
    "liq_arriba_%": 0.03,
    "liq_abajo_%": 0.44,
    "atr_%": 0.488,
    "adx": 69.1,
    "regimen": "tendencia",
    "vol_rel": 1.4
  }
]