[
  {
    "dir": "largo",
    "entry": 1727.0,
    "stop": 1715.8824,
    "target": 1749.2352,
    "status": "cerrada",
    "ts": 1782040500000,
    "estr": "rsidiv",
    "coin": "ETH",
    "tf": "15m",
    "fecha": "2026-06-21 11:15:00",
    "funding": 8.4411e-06,
    "oi": 779258.8255999997,
    "pos_rango": 0.31,
    "liq_arriba_%": 0.07,
    "liq_abajo_%": 0.09,
    "exit": 1715.8824,
    "pnl": -0.007237521713954842,
    "mfe_R": 0.18,
    "mae_R": 1.03,
    "res": "1m"
  },
  {
    "dir": "largo",
    "entry": 1726.0,
    "stop": 1721.277,
    "target": 1735.446,
    "status": "cerrada",
    "ts": 1782041400000,
    "estr": "rsidiv",
    "coin": "ETH",
    "tf": "15m",
    "fecha": "2026-06-21 11:30:00",
    "funding": 8.4411e-06,
    "oi": 779258.8255999997,
    "pos_rango": 0.31,
    "liq_arriba_%": 0.07,
    "liq_abajo_%": 0.09,
    "exit": 1721.277,
    "pnl": -0.0035363847045190903,
    "mfe_R": 0.34,
    "mae_R": 1.02,
    "res": "1m"
  },
  {
    "dir": "largo",
    "entry": 1715.2,
    "stop": 1710.3879,
    "target": 1724.8242000000002,
    "status": "abierta",
    "ts": 1782079200000,
    "estr": "rsidiv",
    "coin": "ETH",
    "tf": "15m",
    "fecha": "2026-06-21 22:00:00",
    "funding": 8.4411e-06,
    "oi": 779258.8255999997,
    "pos_rango": 0.31,
    "liq_arriba_%": 0.07,
    "liq_abajo_%": 0.09
  }
]